goshdb/__init__.py
goshdb/api_wrap/__init__.py
goshdb/api_wrap/auth.py
goshdb/api_wrap/sheet.py
goshdb/api_wrap/spreadsheet.py
goshdb/db.py
goshdb/table.py
goshdb/test/__init__.py
goshdb/test_utils/__init__.py
goshdb/test_utils/test_utils.py
goshdb-0.4.0.dist-info/LICENSE
goshdb-0.4.0.dist-info/METADATA
goshdb-0.4.0.dist-info/WHEEL
goshdb-0.4.0.dist-info/RECORD
