Metadata-Version: 2.1
Name: goshdb
Version: 0.4.0
Summary: GOogle SHeets DataBase - Python client to key-value database based on Google Sheets
Home-page: https://github.com/artoby/goshdb
License: MIT
Keywords: google,sheets,spreadsheet,database,key-value,free,nosql
Author: Artyom Vorobyov
Author-email: artyom.vorobyov@gmail.com
Requires-Python: >=3.10
Classifier: License :: OSI Approved :: MIT License
Classifier: Programming Language :: Python :: 3
Classifier: Programming Language :: Python :: 3.10
Classifier: Programming Language :: Python :: 3.11
Classifier: Programming Language :: Python :: 3.12
Classifier: Topic :: Database
Requires-Dist: google-api-python-client (>=2.128.0)
Requires-Dist: google-auth-httplib2 (>=0.2.0)
Requires-Dist: google-auth-oauthlib (>=1.2.0)
Requires-Dist: openpyxl (>=3.1.0)
Requires-Dist: pytest (>=7.4.0)
Project-URL: Repository, https://github.com/artoby/goshdb
